examples/__init__.py
examples/actions.py
examples/callbacks.py
examples/load_actions.py
examples/load_dags.py
examples/main.py
examples/run_tasks.py
examples/settings.py
examples/setup_db.py
seaflow/__init__.py
seaflow/admin.py
seaflow/apps.py
seaflow/base.py
seaflow/celery.py
seaflow/consts.py
seaflow/models.py
seaflow/params.py
seaflow/seagull.py
seaflow/tasks.py
seaflow/tests.py
seaflow/utils.py
seaflow/migrations/0001_initial.py
seaflow/migrations/__init__.py
seaflow-0.0.1b6.dist-info/LICENSE
seaflow-0.0.1b6.dist-info/METADATA
seaflow-0.0.1b6.dist-info/WHEEL
seaflow-0.0.1b6.dist-info/top_level.txt
seaflow-0.0.1b6.dist-info/RECORD
