Metadata-Version: 2.1
Name: seaflow
Version: 0.0.1b6
Summary: the most free process choreographer
Home-page: https://github.com/rainware/seaflow
Author: rainware
Author-email: kevin90116@gmail.com
License: UNKNOWN
Project-URL: Source, https://github.com/rainware/seaflow
Platform: any
Classifier: Programming Language :: Python :: 3
Classifier: License :: OSI Approved :: MIT License
Classifier: Operating System :: OS Independent
Requires-Python: >=3.6
License-File: LICENSE
Requires-Dist: django (>=3.1)
Requires-Dist: mysqlclient (>=1.4.4)
Requires-Dist: django-extensions (>=3.0.3)
Requires-Dist: celery (>=5.2.1)
Requires-Dist: django-celery-results (>=2.2.0)
Requires-Dist: redis (>=3.5.3)
Requires-Dist: flower (>=1.0.0)
Requires-Dist: django-mysql (>=3.8.1)
Requires-Dist: timeout-decorator (>=0.4.1)
Requires-Dist: jsonpath-rw (>=1.4.0)
Requires-Dist: json-logic-qubit (>=0.9.1)
